cloudio/__init__.py
cloudio/glue/__init__.py
cloudio/glue/cloudio_attribute.py
cloudio/glue/model_to_cloud_connector.py
cloudio/glue/version.py
cloudio_glue_python-1.0.3.dist-info/LICENSE
cloudio_glue_python-1.0.3.dist-info/METADATA
cloudio_glue_python-1.0.3.dist-info/WHEEL
cloudio_glue_python-1.0.3.dist-info/top_level.txt
cloudio_glue_python-1.0.3.dist-info/RECORD
