Metadata-Version: 2.1
Name: cloudio-glue-python
Version: 1.0.3
Summary: cloud.iO endpoint glue
Home-page: https://cloudio.hevs.ch
Author: HES-SO Valais, School of Engineering, Sion
Author-email: thomas.sterren@hevs.ch
License: MIT
Project-URL: Bug Tracker, https://github.com/boozo-unlimited/cloudio-glue-python/issues
Project-URL: Source Code, https://github.com/boozo-unlimited/cloudio-glue-python
Project-URL: Documentation, https://github.com/boozo-unlimited/cloudio-glue-python#cloudio-glue
Keywords: cloud.iO endpoint library IoT cloud connector model
Classifier: Development Status :: 5 - Production/Stable
Classifier: Intended Audience :: Developers
Classifier: Intended Audience :: Education
Classifier: Intended Audience :: Science/Research
Classifier: Intended Audience :: Information Technology
Classifier: Topic :: Software Development :: Libraries :: Python Modules
Classifier: License :: OSI Approved :: MIT License
Classifier: Programming Language :: Python :: 3.8
Classifier: Programming Language :: Python :: 3.9
Classifier: Operating System :: OS Independent
License-File: LICENSE
Requires-Dist: cloudio-endpoint-python
